{
  "title": "Episodio: 22 impresora RENDERIZAR",
  "content": "\n?Script?\n\n[empleado_1] (4 segundos | Confundido | Se masajea las sienes)\r\r\r\r1. A ver, expliquen esto otra vez? (PP empleado_1)\r\r2. ?C?mo que desaparecieron 4,000 impresoras? (PA-I*1.3)\r\r3. OSD (?Eh?) (PP empleado_1)\r\r\r\r[empleado_2] (4 segundos | Inc?modo | Se encoge de hombros)\r\r\r\r1. Bueno, t?cnicamente? nunca existieron. (PP empleado_2)\r\r2. OSD (Dum!) (ZO*1.5)\r\r\r\r[empleado_1] (4 segundos | Indignado | Mira los papeles en su escritorio)\r\r\r\r1. ?C?mo que nunca existieron? (PP empleado_1)\r\r2. ?Est?n en los registros contables! (PA-D*1.3)\r\r\r\r[empleado_3] (4 segundos | Explicando con calma | Mira al techo)\r\r\r\r1. S?, pero en la realidad, no. (PP empleado_3)\r\r2. Esas impresoras solo exist?an en el sistema. (PA-I*1.5)\r\r3. OSD (Dum!) (ZO*1.5)\r\r\r\r[empleado_1] (5 segundos | At?nito | Baja los papeles lentamente)\r\r\r\r1. Pero ni siquiera vendemos impresoras? (PP empleado_1)\r\r2. A duras penas hay papel en el ba?o. (PA-D*1.3)\r\r3. Y aqu? dice que factur? millones? (PP empleado_1)\r\r4. ?Y nadie lo not? en tres a?os? (ZI*1.5)\r\r5. OSD (Hmm) (PP empleado_1)\r\r\r\r[empleado_2] (3 segundos | Encogiendo los hombros | Sonrisa inc?moda)\r\r\r\r1. As? es. (PP empleado_2)\r\r\r\r[empleado_1] (4 segundos | Frunce el ce?o | Cruza los brazos)\r\r\r\r1. ?Y qu? modelo era? (PP empleado_1)\r\r\r\r[empleado_3] (4 segundos | Bajando la voz | Se inclina hacia adelante)\r\r\r\r1. Turquesa ne?n. (PP empleado_3)\r\r2. OSD (Dum!) (ZO*1.5)\r\r\r\r[empleado_1] (5 segundos | Pausa dram?tica | Parpadea lentamente)\r\r\r\r1. ?Y a nadie le pareci? sospechoso? (PA-D*1.3)\r\r2. OSD (Hmm) (PP empleado_1)\r\r\r\r[empleado_2] (4 segundos | A la defensiva | Se encoge de hombros)\r\r\r\r1. Pues? no. (PP empleado_2)\r\r\r\r[empleado_1] (4 segundos | Perplejo | Mira a ambos)\r\r\r\r1. O sea que vendimos aire con WiFi? (PA-I*1.3)\r\r2. OSD (?Eh?) (PP empleado_1)\r\r\r\r[empleado_2] (5 segundos | Con orgullo | Sonr?e confiado)\r\r\r\r1. Y con Bluetooth. (PA-D*1.2)\r\r2. OSD (Dum!) (ZO*1.5)\r\r\r\r[empleado_3] (4 segundos | Sonrisa nerviosa | Mueve los dedos sobre el escritorio)\r\r\r\r1. Pero? ?qu? podemos deducir de esto? (PP empleado_3)\r\r\r\r[empleado_2] (4 segundos | Sonrisa orgullosa | Se?ala una pantalla)\r\r\r\r1. Que no hay que juzgar a una impresora? (PP empleado_2)\r\r2. Por su color. (PA-D*1.3)\r\r3. OSD (Dum!) (ZO*1.5)\r\r\r\r[empleado_1] (5 segundos | Silencio absoluto | Se queda inm?vil)\r\r\r\r1. A? (ZO*1.5)\r\r2. OSD (Dum!) (ZO*2.5)\r\r\r\r**OFICINA**\r\r",
  "url": "https://docs.google.com/document/d/1SHBmzoCg_d0mFPQDoHMmG7x51gfBYgiWxPjl25PEips/edit?usp=drivesdk",
  "status": "procesar",
  "sendDate": "20250308094102"
}